hipchav
