Metadata-Version: 1.0
Name: hipchav
Version: 0.1.3
Summary: A minimal command-line HipChat client.
Home-page: https://github.com/larsyencken/hipchav/
Author: Lars Yencken
Author-email: lars@yencken.org
License: ISC
Platform: UNKNOWN
